__init__.py
UofA_BAJA_2023_2024_common/Messages.py
UofA_BAJA_2023_2024_common/SerialDevices.py
UofA_BAJA_2023_2024_common/__init__.py
UofA_BAJA_2023_2024_common/enums.py
UofA_BAJA_2023_2024-0.1.6.dist-info/LICENSE
UofA_BAJA_2023_2024-0.1.6.dist-info/METADATA
UofA_BAJA_2023_2024-0.1.6.dist-info/WHEEL
UofA_BAJA_2023_2024-0.1.6.dist-info/top_level.txt
UofA_BAJA_2023_2024-0.1.6.dist-info/RECORD
